pip_depender/__init__.py
pip_depender/cli.py
pip_depender-0.2.0.dist-info/LICENSE
pip_depender-0.2.0.dist-info/METADATA
pip_depender-0.2.0.dist-info/WHEEL
pip_depender-0.2.0.dist-info/entry_points.txt
pip_depender-0.2.0.dist-info/RECORD
