Metadata-Version: 2.3
Name: pip-depender
Version: 0.2.0
Summary: Depender: Streamline your Python project dependencies with intelligent version management
License: MIT
Author: chyroc
Author-email: chyroc@qq.com
Requires-Python: >=3.8,<4.0
Classifier: License :: OSI Approved :: MIT License
Classifier: Programming Language :: Python :: 3
Classifier: Programming Language :: Python :: 3.8
Classifier: Programming Language :: Python :: 3.9
Classifier: Programming Language :: Python :: 3.10
Classifier: Programming Language :: Python :: 3.11
Classifier: Programming Language :: Python :: 3.12
Classifier: Programming Language :: Python :: 3.13
Requires-Dist: click (>=8.1.7,<9.0.0)
Requires-Dist: httpx (>=0.25.0,<0.26.0)
Requires-Dist: packaging (>=23.2,<24.0)
